Metadata-Version: 1.0
Name: prefepy
Version: 0.0.1
Summary: Prefence manager module to gather and show content to users
Home-page: http://github.com/ballcarsen/
Author: Carsen Ball
Author-email: carsen@NEXTstory.com
License: Next Story Group, Carsen Ball
Platform: UNKNOWN
